Workbook

Sheet Backup Dirty Data
A1: Sales_Order # | B1: Date | C1: Day | D1: Month | E1: Year | F1: Customer_Age | G1: Age_Group | H1: Customer_Gender | I1: Country | J1: State | K1: Product_Category | L1: Sub_Category | M1: Product_Description | N1: Order_Quantity | O1: Unit_Cost | P1: Unit_Price | Q1: Profit | R1: Cost | S1: Revenue
A2: 000261695 | B2: 44531 | C2: 1 | D2: December | E2: 2021 | F2: 39 | G2: Adults (35-64) | H2: F | I2: United States | J2: California | K2: Bikes | L2: Mountain Bikes | M2: Mountain-200 Black, 46 | N2: 4 | O2: 1252 | P2: 2295 | Q2: 4172 | R2: =N2*O2 -> 5008 | S2: =N2*P2 -> 9180
A3: 000261695 | B3: 44531 | C3: 1 | D3: December | E3: 2021 | F3: 44 | G3: Adults (35-64) | H3: M | I3: United Kingdom | J3: England | K3: Bikes | L3: Mountain Bikes | M3: Mountain-200 Silver, 42 | N3: 1 | O3: 1266 | P3: 2320 | Q3: 1054 | R3: =N3*O3 -> 1266 | S3: =N3*P3 -> 2320
A4: 000261697 | B4: 44532 | C4: 2 | D4: December | E4: 2021 | F4: 37 | G4: Adults (35-64) | H4: M | I4: United States | J4: California | K4: Bikes | L4: Mountain Bikes | M4: Mountain-400-W Silver, 46 | N4: 2 | O4: 420 | P4: 769 | Q4: 698 | R4: =N4*O4 -> 840 | S4: =N4*P4 -> 1538
A5: 000261698 | B5: 44532 | C5: 2 | D5: December | E5: 2021 | F5: 31 | G5: Young Adults (25-34) | H5: F | I5: Australia | J5: New South Wales | K5: Bikes | L5: Mountain Bikes | M5: Mountain-400-W Silver, 42 | N5: 1 | O5: 420 | P5: 769 | Q5: 349 | R5: =N5*O5 -> 420 | S5: =N5*P5 -> 769
A6: 000261699 | B6: 44533 | C6: 3 | D6: December | E6: 2021 | F6: 37 | G6: Adults (35-64) | H6: F | I6: United States | J6: California | K6: Bikes | L6: Mountain Bikes | M6: Mountain-200 Black, 46 | N6: 2 | O6: 0 | P6: 2295 | Q6: 2086 | R6: =N6*O6 -> 0 | S6: =N6*P6 -> 4590
A7: 000261700 | B7: 44533 | C7: 3 | D7: December | E7: 2021 | F7: 24 | G7: Youth (<25) | H7: F | I7: United Kingdom | J7: England | K7: Bikes | L7: Mountain Bikes | M7: Mountain-200 Black, 38 | N7: 1 | O7: 1252 | P7: 2295 | Q7: 1043 | R7: =N7*O7 -> 1252 | S7: =N7*P7 -> 2295
A8: 000261701 | B8: 44533 | C8: 3 | D8: December | E8: 2021 | F8: 37 | G8: Adults (35-64) | H8: M | I8: United States | J8: Washington | K8: Bikes | L8: Mountain Bikes | M8: Mountain-200 Black, 46 | N8: 1 | O8: 1252 | P8: 2295 | Q8: 1043 | R8: =N8*O8 -> 1252 | S8: =N8*P8 -> 2295
A9: 000261701 | B9: 44533 | C9: 3 | D9: December | E9: 2021 | F9: 37 | G9: Adults (35-64) | H9: M | I9: United States | J9: Washington | K9: Bikes | L9: Mountain Bikes | M9: Mountain-200 Black, 46 | N9: 1 | O9: 1252 | P9: 2295 | Q9: 1043 | R9: =N9*O9 -> 1252 | S9: =N9*P9 -> 2295
A10: 000261702 | B10: 44534 | C10: 4 | D10: December | E10: 2021 | F10: 31 | G10: Young Adults (25-34) | H10: F | I10: Australia | J10: New South Wales | K10: Bikes | L10: Mountain Bikes | M10: Mountain-400-W Silver, 42 | N10: 4 | O10: 420 | P10: 0 | Q10: 1396 | R10: =N10*O10 -> 1680 | S10: =N10*P10 -> 0
A11: 000261703 | B11: 44535 | C11: 5 | D11: December | E11: 2021 | F11: 39 | G11: Adults (35-64) | H11: F | I11: United States | J11: California | K11: Bikes | L11: Mountain Bikes | M11: Mountain-200 Black, 46 | N11: 4 | O11: 1252 | P11: 2295 | Q11: 4172 | R11: =N11*O11 -> 5008 | S11: =N11*P11 -> 9180
A12: 000261704 | B12: 44535 | D12: December | E12: 2021 | F12: 42 | G12: Adults (35-64) | H12: M | I12: Germany | J12: Nordrhein-Westfalen | K12: Bikes | L12: Mountain Bikes | M12: Mountain-200 Black, 38 | N12: 4 | O12: 1252 | P12: 2295 | Q12: 4172 | R12: =N12*O12 -> 5008 | S12: =N12*P12 -> 9180
A13: 000261705 | B13: 44535 | C13: 5 | D13: December | E13: 2021 | F13: 35 | G13: Adults (35-64) | H13: F | I13: Australia | J13: Queensland | K13: Bikes | L13: Mountain Bikes | M13: Mountain-200 Silver, 38 | N13: 1 | O13: 1266 | P13: 2320 | Q13: 1054 | R13: =N13*O13 -> 1266 | S13: =N13*P13 -> 2320
A14: 000261706 | B14: 44535 | C14: 5 | D14: December | E14: 2021 | F14: 37 | G14: Adults (35-64) | H14: F | I14: United States | J14: California | K14: Bikes | L14: Mountain Bikes | M14: Mountain-200 Black, 46 | N14: 1 | O14: 1252 | P14: 2295 | Q14: 1043 | R14: =N14*O14 -> 1252 | S14: =N14*P14 -> 2295
A15: 000261707 | B15: 44536 | C15: 6 | D15: December | E15: 2021 | F15: 23 | G15: Youth (<25) | H15: M | I15: United Kingdom | J15: England | K15: Bikes | L15: Mountain Bikes | M15: Mountain-400-W Silver, 46 | N15: 3 | O15: 420 | P15: 769 | Q15: 1047 | R15: =N15*O15 -> 1260 | S15: =N15*P15 -> 2307
A16: 000261708 | B16: 44536 | C16: 6 | D16: December | E16: 2021 | F16: 27 | G16: Young Adults (25-34) | H16: M | I16: Canada | J16: British Columbia | K16: Bikes | L16: Mountain Bikes | M16: Mountain-200 Black, 46 | N16: 1 | O16: 1252 | P16: 2295 | Q16: 1043 | R16: =N16*O16 -> 1252 | S16: =N16*P16 -> 2295
A17: 000261709 | B17: 44536 | C17: 6 | D17: December | E17: 2021 | F17: 36 | H17: M | I17: Australia | J17: New South Wales | K17: Bikes | L17: Mountain Bikes | M17: Mountain-200 Black, 42 | N17: 1 | O17: 1252 | P17: 2295 | Q17: 1043 | R17: =N17*O17 -> 1252 | S17: =N17*P17 -> 2295
A18: 000261710 | B18: 44536 | C18: 6 | D18: December | E18: 2021 | F18: 47 | G18: Adults (35-64) | H18: M | I18: United Kingdom | J18: England | K18: Bikes | L18: Mountain Bikes | M18: Mountain-200 Silver, 38 | N18: 1 | O18: 1266 | P18: 2320 | Q18: 1054 | R18: =N18*O18 -> 1266 | S18: =N18*P18 -> 2320
A19: 000261711 | B19: 44537 | C19: 7 | D19: Decmber | E19: 2021 | F19: 30 | G19: Young Adults (25-34) | H19: M | I19: United States | J19: California | K19: Bikes | L19: Mountain Bikes | M19: Mountain-400-W Silver, 38 | N19: 4 | O19: 420 | P19: 769 | Q19: 1396 | R19: =N19*O19 -> 1680 | S19: =N19*P19 -> 3076
A20: 000261712 | B20: 44537 | C20: 7 | D20: December | E20: 2021 | F20: 38 | G20: Adults (35-64) | H20: M | I20: United States | J20: California | K20: Bikes | L20: Mountain Bikes | M20: Mountain-200 Silver, 42 | N20: 2 | O20: 1266 | P20: 2320 | Q20: 2108 | R20: =N20*O20 -> 2532 | S20: =N20*P20 -> 4640
A21: 000261713 | B21: 44538 | C21: 8 | D21: December | E21: 2021 | F21: 19 | G21: Youth (<25) | H21: F | I21: Australia | J21: New South Wales | K21: Bikes | L21: Mountain Bikes | M21: Mountain-500 Silver, 42 | N21: 4 | O21: 308 | P21: 565 | Q21: 1028 | R21: =N21*O21 -> 1232 | S21: =N21*P21 -> 2260
A22: 000261714 | B22: 44538 | C22: 8 | D22: December | E22: 2021 | F22: 30 | G22: Young Adults (25-34) | H22: F | I22: Canada | J22: British Columbia | K22: Bikes | L22: Mountain Bikes | M22: Mountain-200 Silver, 38 | N22: 4 | O22: 1266 | P22: 2320 | Q22: 4216 | R22: =N22*O22 -> 5064 | S22: =N22*P22 -> 9280
A23: 000261715 | B23: 44538 | C23: 8 | D23: December | E23: 2021 | F23: 39 | G23: Adults (35-64) | H23: F | I23: United States | J23: Oregon | K23: Bikes | L23: Mountain Bikes | N23: 2 | O23: 1252 | P23: 2295 | Q23: 2086 | R23: =N23*O23 -> 2504 | S23: =N23*P23 -> 4590
A24: 000261716 | B24: 44538 | C24: 8 | D24: December | E24: 2021 | F24: 35 | G24: Adults (35-64) | H24: F | I24: United States | J24: California | K24: Bikes | L24: Mountain Bikes | M24: Mountain-500 Black, 42 | O24: 295 | P24: 540 | Q24: 245 | R24: =N24*O24 -> 0 | S24: =N24*P24 -> 0
A25: 000261717 | B25: 44539 | C25: 9 | D25: December | E25: 2021 | F25: 33 | G25: Young Adults (25-34) | H25: F | I25: Australia | J25: Victoria | K25: Bikes | L25: Mountain Bikes | M25: Mountain-100 Black, 38 | N25: 2 | O25: 1898 | P25: 3375 | Q25: 2954 | R25: =N25*O25 -> 3796 | S25: =N25*P25 -> 6750
A26: 000261718 | B26: 44539 | C26: 9 | D26: December | E26: 2021 | F26: 41 | G26: Adults (35-64) | H26: F | I26: Germany | J26: Hamburg | K26: Bikes | L26: Mountain Bikes | M26: Mountain-200 Silver, 42 | N26: 1 | O26: 1266 | P26: 2320 | Q26: 1054 | R26: =N26*O26 -> 1266 | S26: =N26*P26 -> 2320
A27: 000261719 | B27: 44540 | C27: 10 | D27: December | E27: 2021 | F27: 34 | G27: Young Adults (25-34) | H27: F | I27: United States | J27: California | K27: Bikes | L27: Mountain Bikes | M27: Mountain-200 Black, 42 | N27: 2 | O27: 1252 | P27: 2295 | Q27: 2086 | R27: =N27*O27 -> 2504 | S27: =N27*P27 -> 4590
A28: 000261720 | B28: 44540 | C28: 10 | D28: December | E28: 2021 | F28: 40 | G28: Adults (35-64) | H28: M | I28: Australia | J28: New South Wales | K28: Bikes | L28: Mountain Bikes | M28: Mountain-200 Black, 42 | N28: 2 | O28: 1252 | P28: 2295 | Q28: 2086 | R28: =N28*O28 -> 2504 | S28: =N28*P28 -> 4590
A29: 000261721 | B29: 44540 | C29: 10 | D29: December | E29: 2021 | F29: 26 | G29: Young Adults (25-34) | H29: M | I29: United Kingdom | J29: England | K29: Bikes | L29: Mountain Bikes | M29: Mountain-200 Black, 38 | N29: 1 | O29: 1252 | P29: 2295 | Q29: 1043 | R29: =N29*O29 -> 1252 | S29: =N29*P29 -> 2295
A30: 000261722 | B30: 44540 | C30: 10 | D30: December | E30: 2021 | F30: 34 | G30: Young Adults (25-34) | H30: M | I30: United States | J30: California | K30: Bikes | L30: Mountain Bikes | M30: Mountain-500 Black, 40 | N30: 1 | O30: 295 | P30: 540 | Q30: 245 | R30: =N30*O30 -> 295 | S30: =N30*P30 -> 540
A31: 000261723 | B31: 44540 | C31: 10 | D31: December | E31: 2021 | F31: 34 | G31: Young Adults (25-34) | H31: F | I31: United States | J31: Washington | K31: Bikes | L31: Mountain Bikes | M31: Mountain-100 Silver, 44 | N31: 1 | O31: 1912 | P31: 3400 | Q31: 1488 | R31: =N31*O31 -> 1912 | S31: =N31*P31 -> 3400
A32: 000261724 | B32: 44540 | C32: 10 | D32: December | E32: 2021 | F32: 38 | G32: Adults (35-64) | H32: M | I32: Australia | J32: New South Wales | K32: Bikes | L32: Mountain Bikes | M32: Mountain-200 Black, 38 | N32: 1 | O32: 1252 | P32: 2295 | Q32: 1043 | R32: =N32*O32 -> 1252 | S32: =N32*P32 -> 2295
A33: 000261725 | B33: 44541 | C33: 11 | D33: December | E33: 2021 | F33: 24 | G33: Youth (<25) | H33: F | I33: France | J33: Seine (Paris) | K33: Bikes | L33: Mountain Bikes | M33: Mountain-200 Black, 38 | N33: 3 | O33: 1252 | P33: 2295 | Q33: 3129 | R33: =N33*O33 -> 3756 | S33: =N33*P33 -> 6885
A34: 000261726 | B34: 44541 | C34: 11 | D34: December | E34: 2021 | F34: 41 | G34: Adults (35-64) | H34: F | I34: Australia | J34: New South Wales | K34: Bikes | L34: Mountain Bikes | M34: Mountain-400-W Silver, 38 | N34: 2 | O34: 420 | P34: 769 | Q34: 698 | R34: =N34*O34 -> 840 | S34: =N34*P34 -> 1538
A35: 000261727 | B35: 44541 | C35: 11 | D35: December | E35: 2021 | F35: 27 | G35: Young Adults (25-34) | H35: M | I35: Canada | J35: British Columbia | K35: Bikes | L35: Mountain Bikes | M35: Mountain-200 Black, 46 | N35: 1 | O35: 1252 | P35: 2295 | Q35: 1043 | R35: =N35*O35 -> 1252 | S35: =N35*P35 -> 2295
A36: 000261728 | B36: 44541 | C36: 11 | D36: December | E36: 2021 | F36: 37 | G36: Adults (35-64) | H36: M | I36: United States | J36: California | K36: Bikes | L36: Mountain Bikes | M36: Mountain-400-W Silver, 46 | N36: 1 | O36: 420 | P36: 769 | Q36: 349 | R36: =N36*O36 -> 420 | S36: =N36*P36 -> 769
... A90: 000261782 | B90: 44554 | C90: 24 | D90: December | E90: 2021 | F90: 38 | G90: Adults (35-64) | H90: M | I90: Australia | J90: Queensland | K90: Bikes | L90: Mountain Bikes | M90: Mountain-200 Black, 42 | N90: 4 | O90: 1252 | P90: 2295 | Q90: 4172 | R90: =N90*O90 -> 5008 | S90: =N90*P90 -> 9180

Sheet Fact_Revenue
A1: Order_ID | B1: Sales_Order # | C1: Date | D1: Date_ID | E1: Day | F1: Month | G1: Year | H1: Customer_ID | I1: Customer_Age | J1: Age_Group | K1: Customer_Gender | L1: Country | M1: State | N1: Product_ID | O1: Product_Category | P1: Sub_Category | Q1: Model | R1: Color | S1: Size | T1: Order_Quantity | U1: Unit_Cost | V1: Unit_Price | W1: Profit | X1: Cost | Y1: Revenue
A2: =VLOOKUP(B2,Order_Dim!A2:B89,2,1) -> S-101 | B2: 000261695 | C2: 44531 | D2: =VLOOKUP(C2,Date_Dim!A2:B89,2,1) -> 20211201 | E2: 1 | F2: December | G2: 2021 | H2: =VLOOKUP(I2,'Customer_Dim'!A2:B89,2,1) -> C-141 | I2: 39 | J2: Adults (35-64) | K2: Female | L2: United States | M2: California | N2: =VLOOKUP(O1,Product_Dim!A2:B89,2,1) -> P-188 | O2: Bikes | P2: Mountain Bikes | Q2: Mountain-200 | R2: Black | S2: 46 | T2: 4 | U2: 1252 | V2: 2295 | W2: 4172 | X2: =T2*U2 -> 5008 | Y2: =T2*V2 -> 9180
A3: =VLOOKUP(B3,Order_Dim!A3:B90,2,1) -> S-102 | B3: 261696 | C3: 44531 | D3: =VLOOKUP(C3,Date_Dim!A3:B90,2,1) -> 20211201 | E3: 1 | F3: December | G3: 2021 | H3: =VLOOKUP(I3,'Customer_Dim'!A3:B90,2,1) -> C-188 | I3: 44 | J3: Adults (35-64) | K3: Male | L3: United Kingdom | M3: England | N3: =VLOOKUP(O2,Product_Dim!A3:B90,2,1) -> P-188 | O3: Bikes | P3: Mountain Bikes | Q3: Mountain-200 | R3: Silver | S3: 42 | T3: 1 | U3: 1266 | V3: 2320 | W3: 1054 | X3: =T3*U3 -> 1266 | Y3: =T3*V3 -> 2320
A4: =VLOOKUP(B4,Order_Dim!A4:B91,2,1) -> S-103 | B4: 000261697 | C4: 44532 | D4: =VLOOKUP(C4,Date_Dim!A4:B91,2,1) -> 20211202 | E4: 2 | F4: December | G4: 2021 | H4: =VLOOKUP(I4,'Customer_Dim'!A4:B91,2,1) -> C-166 | I4: 37 | J4: Adults (35-64) | K4: Male | L4: United States | M4: California | N4: =VLOOKUP(O3,Product_Dim!A4:B91,2,1) -> P-188 | O4: Bikes | P4: Mountain Bikes | Q4: Mountain-400-W | R4: Silver | S4: 46 | T4: 2 | U4: 420 | V4: 769 | W4: 698 | X4: =T4*U4 -> 840 | Y4: =T4*V4 -> 1538
A5: =VLOOKUP(B5,Order_Dim!A5:B92,2,1) -> S-104 | B5: 000261698 | C5: 44532 | D5: =VLOOKUP(C5,Date_Dim!A5:B92,2,1) -> 20211202 | E5: 2 | F5: December | G5: 2021 | H5: =VLOOKUP(I5,'Customer_Dim'!A5:B92,2,1) -> C-120 | I5: 31 | J5: Young Adults (25-34) | K5: Female | L5: Australia | M5: New South Wales | N5: =VLOOKUP(O4,Product_Dim!A5:B92,2,1) -> P-188 | O5: Bikes | P5: Mountain Bikes | Q5: Mountain-400-W | R5: Silver | S5: 42 | T5: 1 | U5: 420 | V5: 769 | W5: 349 | X5: =T5*U5 -> 420 | Y5: =T5*V5 -> 769
A6: =VLOOKUP(B6,Order_Dim!A6:B93,2,1) -> S-105 | B6: 000261699 | C6: 44533 | D6: =VLOOKUP(C6,Date_Dim!A6:B93,2,1) -> 20211203 | E6: 3 | F6: December | G6: 2021 | H6: =VLOOKUP(I6,'Customer_Dim'!A6:B93,2,1) -> C-153 | I6: 37 | J6: Adults (35-64) | K6: Female | L6: United States | M6: California | N6: =VLOOKUP(O5,Product_Dim!A6:B93,2,1) -> P-188 | O6: Bikes | P6: Mountain Bikes | Q6: Mountain-200 | R6: Black | S6: 46 | T6: 2 | U6: 1252 | V6: 2295 | W6: 2086 | X6: =T6*U6 -> 2504 | Y6: =T6*V6 -> 4590
A7: =VLOOKUP(B7,Order_Dim!A7:B94,2,1) -> S-106 | B7: 000261700 | C7: 44533 | D7: =VLOOKUP(C7,Date_Dim!A7:B94,2,1) -> 20211203 | E7: 3 | F7: December | G7: 2021 | H7: =VLOOKUP(I7,'Customer_Dim'!A7:B94,2,1) -> C-106 | I7: 24 | J7: Youth (<25) | K7: Female | L7: United Kingdom | M7: England | N7: =VLOOKUP(O6,Product_Dim!A7:B94,2,1) -> P-188 | O7: Bikes | P7: Mountain Bikes | Q7: Mountain-200 | R7: Black | S7: 38 | T7: 1 | U7: 1252 | V7: 2295 | W7: 1043 | X7: =T7*U7 -> 1252 | Y7: =T7*V7 -> 2295
A8: =VLOOKUP(B8,Order_Dim!A8:B95,2,1) -> S-107 | B8: 000261701 | C8: 44533 | D8: =VLOOKUP(C8,Date_Dim!A8:B95,2,1) -> 20211203 | E8: 3 | F8: December | G8: 2021 | H8: =VLOOKUP(I8,'Customer_Dim'!A8:B95,2,1) -> C-141 | I8: 37 | J8: Adults (35-64) | K8: Male | L8: United States | M8: Washington | N8: =VLOOKUP(O7,Product_Dim!A8:B95,2,1) -> P-188 | O8: Bikes | P8: Mountain Bikes | Q8: Mountain-200 | R8: Black | S8: 46 | T8: 1 | U8: 1252 | V8: 2295 | W8: 1043 | X8: =T8*U8 -> 1252 | Y8: =T8*V8 -> 2295
A9: =VLOOKUP(B9,Order_Dim!A9:B96,2,1) -> S-108 | B9: 000261702 | C9: 44534 | D9: =VLOOKUP(C9,Date_Dim!A9:B96,2,1) -> 20211204 | E9: 4 | F9: December | G9: 2021 | H9: =VLOOKUP(I9,'Customer_Dim'!A9:B96,2,1) -> C-164 | I9: 31 | J9: Young Adults (25-34) | K9: Female | L9: Australia | M9: New South Wales | N9: =VLOOKUP(O8,Product_Dim!A9:B96,2,1) -> P-188 | O9: Bikes | P9: Mountain Bikes | Q9: Mountain-400-W | R9: Silver | S9: 42 | T9: 4 | U9: 420 | V9: 769 | W9: 1396 | X9: =T9*U9 -> 1680 | Y9: =T9*V9 -> 3076
A10: =VLOOKUP(B10,Order_Dim!A10:B97,2,1) -> S-109 | B10: 000261703 | C10: 44535 | D10: =VLOOKUP(C10,Date_Dim!A10:B97,2,1) -> 20211205 | E10: 5 | F10: December | G10: 2021 | H10: =VLOOKUP(I10,'Customer_Dim'!A10:B97,2,1) -> C-188 | I10: 39 | J10: Adults (35-64) | K10: Female | L10: United States | M10: California | N10: =VLOOKUP(O9,Product_Dim!A10:B97,2,1) -> P-188 | O10: Bikes | P10: Mountain Bikes | Q10: Mountain-200 | R10: Black | S10: 46 | T10: 4 | U10: 1252 | V10: 2295 | W10: 4172 | X10: =T10*U10 -> 5008 | Y10: =T10*V10 -> 9180
A11: =VLOOKUP(B11,Order_Dim!A11:B98,2,1) -> S-110 | B11: 000261704 | C11: 44535 | D11: =VLOOKUP(C11,Date_Dim!A11:B98,2,1) -> 20211205 | E11: 5 | F11: December | G11: 2021 | H11: =VLOOKUP(I11,'Customer_Dim'!A11:B98,2,1) -> C-188 | I11: 42 | J11: Adults (35-64) | K11: Male | L11: Germany | M11: Nordrhein-Westfalen | N11: =VLOOKUP(O10,Product_Dim!A11:B98,2,1) -> P-188 | O11: Bikes | P11: Mountain Bikes | Q11: Mountain-200 | R11: Black | S11: 38 | T11: 4 | U11: 1252 | V11: 2295 | W11: 4172 | X11: =T11*U11 -> 5008 | Y11: =T11*V11 -> 9180
A12: =VLOOKUP(B12,Order_Dim!A12:B99,2,1) -> S-111 | B12: 000261705 | C12: 44535 | D12: =VLOOKUP(C12,Date_Dim!A12:B99,2,1) -> 20211205 | E12: 5 | F12: December | G12: 2021 | H12: =VLOOKUP(I12,'Customer_Dim'!A12:B99,2,1) -> C-111 | I12: 35 | J12: Adults (35-64) | K12: Female | L12: Australia | M12: Queensland | N12: =VLOOKUP(O11,Product_Dim!A12:B99,2,1) -> P-188 | O12: Bikes | P12: Mountain Bikes | Q12: Mountain-200 | R12: Silver | S12: 38 | T12: 1 | U12: 1266 | V12: 2320 | W12: 1054 | X12: =T12*U12 -> 1266 | Y12: =T12*V12 -> 2320
A13: =VLOOKUP(B13,Order_Dim!A13:B100,2,1) -> S-112 | B13: 000261706 | C13: 44535 | D13: =VLOOKUP(C13,Date_Dim!A13:B100,2,1) -> 20211205 | E13: 5 | F13: December | G13: 2021 | H13: =VLOOKUP(I13,'Customer_Dim'!A13:B100,2,1) -> C-187 | I13: 37 | J13: Adults (35-64) | K13: Female | L13: United States | M13: California | N13: =VLOOKUP(O12,Product_Dim!A13:B100,2,1) -> P-188 | O13: Bikes | P13: Mountain Bikes | Q13: Mountain-200 | R13: Black | S13: 46 | T13: 1 | U13: 1252 | V13: 2295 | W13: 1043 | X13: =T13*U13 -> 1252 | Y13: =T13*V13 -> 2295
A14: =VLOOKUP(B14,Order_Dim!A14:B101,2,1) -> S-113 | B14: 000261707 | C14: 44536 | D14: =VLOOKUP(C14,Date_Dim!A14:B101,2,1) -> 20211206 | E14: 6 | F14: December | G14: 2021 | H14: =VLOOKUP(I14,'Customer_Dim'!A14:B101,2,1) -> C-113 | I14: 23 | J14: Youth (<25) | K14: Male | L14: United Kingdom | M14: England | N14: =VLOOKUP(O13,Product_Dim!A14:B101,2,1) -> P-188 | O14: Bikes | P14: Mountain Bikes | Q14: Mountain-400-W | R14: Silver | S14: 46 | T14: 3 | U14: 420 | V14: 769 | W14: 1047 | X14: =T14*U14 -> 1260 | Y14: =T14*V14 -> 2307
A15: =VLOOKUP(B15,Order_Dim!A15:B102,2,1) -> S-114 | B15: 000261708 | C15: 44536 | D15: =VLOOKUP(C15,Date_Dim!A15:B102,2,1) -> 20211206 | E15: 6 | F15: December | G15: 2021 | H15: =VLOOKUP(I15,'Customer_Dim'!A15:B102,2,1) -> C-164 | I15: 27 | J15: Young Adults (25-34) | K15: Male | L15: Canada | M15: British Columbia | N15: =VLOOKUP(O14,Product_Dim!A15:B102,2,1) -> P-188 | O15: Bikes | P15: Mountain Bikes | Q15: Mountain-200 | R15: Black | S15: 46 | T15: 1 | U15: 1252 | V15: 2295 | W15: 1043 | X15: =T15*U15 -> 1252 | Y15: =T15*V15 -> 2295
... A89: =VLOOKUP(B89,Order_Dim!A89:B176,2,1) -> S-188 | B89: 000261782 | C89: 44554 | D89: =VLOOKUP(C89,Date_Dim!A89:B176,2,1) -> 20211224 | E89: 24 | F89: December | G89: 2021 | H89: =VLOOKUP(I89,'Customer_Dim'!A89:B176,2,1) -> C-188 | I89: 38 | J89: Adults (35-64) | K89: Male | L89: Australia | M89: Queensland | N89: =VLOOKUP(O88,Product_Dim!A89:B176,2,1) -> P-188 | O89: Bikes | P89: Mountain Bikes | Q89: Mountain-200 | R89: Black | S89: 42 | T89: 4 | U89: 1252 | V89: 2295 | W89: 4172 | X89: =T89*U89 -> 5008 | Y89: =T89*V89 -> 9180

Sheet Date_Dim
A1: Date | B1: Date_ID | C1: Day | D1: Month | E1: Year
A2: 44531 | B2: =YEAR(A2)&TEXT(MONTH(A2),"00")&TEXT(DAY(A2),"00") -> 20211201 | C2: 1 | D2: December | E2: 2021
A3: 44531 | B3: =YEAR(A3)&TEXT(MONTH(A3),"00")&TEXT(DAY(A3),"00") -> 20211201 | C3: 1 | D3: December | E3: 2021
A4: 44532 | B4: =YEAR(A4)&TEXT(MONTH(A4),"00")&TEXT(DAY(A4),"00") -> 20211202 | C4: 2 | D4: December | E4: 2021
A5: 44532 | B5: =YEAR(A5)&TEXT(MONTH(A5),"00")&TEXT(DAY(A5),"00") -> 20211202 | C5: 2 | D5: December | E5: 2021
A6: 44533 | B6: =YEAR(A6)&TEXT(MONTH(A6),"00")&TEXT(DAY(A6),"00") -> 20211203 | C6: 3 | D6: December | E6: 2021
A7: 44533 | B7: =YEAR(A7)&TEXT(MONTH(A7),"00")&TEXT(DAY(A7),"00") -> 20211203 | C7: 3 | D7: December | E7: 2021
A8: 44533 | B8: =YEAR(A8)&TEXT(MONTH(A8),"00")&TEXT(DAY(A8),"00") -> 20211203 | C8: 3 | D8: December | E8: 2021
A9: 44534 | B9: =YEAR(A9)&TEXT(MONTH(A9),"00")&TEXT(DAY(A9),"00") -> 20211204 | C9: 4 | D9: December | E9: 2021
A10: 44535 | B10: =YEAR(A10)&TEXT(MONTH(A10),"00")&TEXT(DAY(A10),"00") -> 20211205 | C10: 5 | D10: December | E10: 2021
A11: 44535 | B11: =YEAR(A11)&TEXT(MONTH(A11),"00")&TEXT(DAY(A11),"00") -> 20211205 | C11: 5 | D11: December | E11: 2021
A12: 44535 | B12: =YEAR(A12)&TEXT(MONTH(A12),"00")&TEXT(DAY(A12),"00") -> 20211205 | C12: 5 | D12: December | E12: 2021
A13: 44535 | B13: =YEAR(A13)&TEXT(MONTH(A13),"00")&TEXT(DAY(A13),"00") -> 20211205 | C13: 5 | D13: December | E13: 2021
... A89: 44554 | B89: =YEAR(A89)&TEXT(MONTH(A89),"00")&TEXT(DAY(A89),"00") -> 20211224 | C89: 24 | D89: December | E89: 2021

Sheet Customer_Dim
A1: Customer_Age | B1: Customer_ID | C1: Age_Group | D1: Customer_Gender | E1: Country | F1: State
A2: 39 | B2: C-101 | C2: Adults (35-64) | D2: Female | E2: United States | F2: California
A3: 44 | B3: C-102 | C3: Adults (35-64) | D3: Male | E3: United Kingdom | F3: England
A4: 37 | B4: C-103 | C4: Adults (35-64) | D4: Male | E4: United States | F4: California
A5: 31 | B5: C-104 | C5: Young Adults (25-34) | D5: Female | E5: Australia | F5: New South Wales
A6: 37 | B6: C-105 | C6: Adults (35-64) | D6: Female | E6: United States | F6: California
A7: 24 | B7: C-106 | C7: Youth (<25) | D7: Female | E7: United Kingdom | F7: England
A8: 37 | B8: C-107 | C8: Adults (35-64) | D8: Male | E8: United States | F8: Washington
A9: 31 | B9: C-108 | C9: Young Adults (25-34) | D9: Female | E9: Australia | F9: New South Wales
A10: 39 | B10: C-109 | C10: Adults (35-64) | D10: Female | E10: United States | F10: California
A11: 42 | B11: C-110 | C11: Adults (35-64) | D11: Male | E11: Germany | F11: Nordrhein-Westfalen
A12: 35 | B12: C-111 | C12: Adults (35-64) | D12: Female | E12: Australia | F12: Queensland
A13: 37 | B13: C-112 | C13: Adults (35-64) | D13: Female | E13: United States | F13: California
A14: 23 | B14: C-113 | C14: Youth (<25) | D14: Male | E14: United Kingdom | F14: England
... A89: 38 | B89: C-188 | C89: Adults (35-64) | D89: Male | E89: Australia | F89: Queensland

Sheet Product_Dim
A1: Product_Category | B1: Product_ID | C1: Sub_Category | D1: Model | E1: Color | F1: Size
A2: Bikes | B2: P-101 | C2: Mountain Bikes | D2: Mountain-200 | E2: Black | F2: 46
A3: Bikes | B3: P-102 | C3: Mountain Bikes | D3: Mountain-200 | E3: Silver | F3: 42
A4: Bikes | B4: P-103 | C4: Mountain Bikes | D4: Mountain-400-W | E4: Silver | F4: 46
A5: Bikes | B5: P-104 | C5: Mountain Bikes | D5: Mountain-400-W | E5: Silver | F5: 42
A6: Bikes | B6: P-105 | C6: Mountain Bikes | D6: Mountain-200 | E6: Black | F6: 46
A7: Bikes | B7: P-106 | C7: Mountain Bikes | D7: Mountain-200 | E7: Black | F7: 38
A8: Bikes | B8: P-107 | C8: Mountain Bikes | D8: Mountain-200 | E8: Black | F8: 46
A9: Bikes | B9: P-108 | C9: Mountain Bikes | D9: Mountain-400-W | E9: Silver | F9: 42
A10: Bikes | B10: P-109 | C10: Mountain Bikes | D10: Mountain-200 | E10: Black | F10: 46
A11: Bikes | B11: P-110 | C11: Mountain Bikes | D11: Mountain-200 | E11: Black | F11: 38
A12: Bikes | B12: P-111 | C12: Mountain Bikes | D12: Mountain-200 | E12: Silver | F12: 38
A13: Bikes | B13: P-112 | C13: Mountain Bikes | D13: Mountain-200 | E13: Black | F13: 46
A14: Bikes | B14: P-113 | C14: Mountain Bikes | D14: Mountain-400-W | E14: Silver | F14: 46
... A89: Bikes | B89: P-188 | C89: Mountain Bikes | D89: Mountain-200 | E89: Black | F89: 42

Sheet Order_Dim
A1: Sales_Order # | B1: Order_ID
A2: 000261695 | B2: S-101
A3: 261696 | B3: S-102
A4: 000261697 | B4: S-103
A5: 000261698 | B5: S-104
A6: 000261699 | B6: S-105
A7: 000261700 | B7: S-106
A8: 000261701 | B8: S-107
A9: 000261702 | B9: S-108
A10: 000261703 | B10: S-109
A11: 000261704 | B11: S-110
A12: 000261705 | B12: S-111
A13: 000261706 | B13: S-112
A14: 000261707 | B14: S-113
A15: 000261708 | B15: S-114
... A89: 000261782 | B89: S-188
